GAF_microbatch_pytorch/GAF.py
GAF_microbatch_pytorch/__init__.py
gaf_microbatch_pytorch-0.0.5.dist-info/METADATA
gaf_microbatch_pytorch-0.0.5.dist-info/WHEEL
gaf_microbatch_pytorch-0.0.5.dist-info/licenses/LICENSE
gaf_microbatch_pytorch-0.0.5.dist-info/RECORD
