Metadata-Version: 2.4
Name: GAF-microbatch-pytorch
Version: 0.0.5
Summary: Gradient Agreement Filtering
Project-URL: Homepage, https://pypi.org/project/GAF-microbatch-pytorch/
Project-URL: Repository, https://github.com/lucidrains/GAF-microbatch-pytorch
Author-email: Phil Wang <lucidrains@gmail.com>
License: MIT License
License-File: LICENSE
Keywords: artificial intelligence,deep learning,gradient filtering,label noise
Classifier: Development Status :: 4 - Beta
Classifier: Intended Audience :: Developers
Classifier: License :: OSI Approved :: MIT License
Classifier: Programming Language :: Python :: 3.9
Classifier: Topic :: Scientific/Engineering :: Artificial Intelligence
Requires-Python: >=3.9
Requires-Dist: einops>=0.8.0
Requires-Dist: torch>=2.4
Provides-Extra: examples
Provides-Extra: test
Requires-Dist: pytest; extra == 'test'
